demo/pipeline/phase2/spark_transform.py
demo/spark_delta/run_spark_query.py
demo/spark_minio_delta/run_spark_query.py
demo/spark_minio_postgres/run_spark_query.py
examples/export_postgres_parquet/run_manual.py
examples/export_redshift_unload/run_manual.py
examples/preview_s3_file/run_manual.py
sqlxport/__init__.py
sqlxport/config.py
sqlxport/enums.py
sqlxport/redshift_unload.py
sqlxport/api/export.py
sqlxport/cli/__init__.py
sqlxport/cli/main.py
sqlxport/core/__init__.py
sqlxport/core/export_modes.py
sqlxport/core/extract.py
sqlxport/core/s3_config.py
sqlxport/core/storage.py
sqlxport/ddl/__init__.py
sqlxport/ddl/utils.py
sqlxport/formats/base.py
sqlxport/formats/csv_writer.py
sqlxport/formats/parquet_writer.py
sqlxport/formats/registry.py
sqlxport/query_engines/__init__.py
sqlxport/query_engines/athena_engine.py
sqlxport/query_engines/base.py
sqlxport/query_engines/duckdb_engine.py
sqlxport/utils/env.py
sqlxport-0.2.0.dist-info/licenses/LICENSE
tests/conftest.py
tests/e2e/test_cli.py
tests/e2e/test_cli_flags.py
tests/integration/conftest.py
tests/integration/test_export_modes_real.py
tests/integration/test_generate_ddl.py
tests/integration/test_redshift_unload_real.py
tests/integration/test_s3_upload_real.py
tests/integration/test_validate_table.py
tests/unit/test_api_export.py
tests/unit/test_athena_engine.py
tests/unit/test_csv_writer.py
tests/unit/test_export_modes.py
tests/unit/test_list_s3_objects.py
tests/unit/test_parquet_writer.py
tests/unit/test_preview_local_parquet.py
tests/unit/test_redshift_unload.py
tests/unit/test_redshift_unload_statement.py
tests/unit/test_s3_provider_and_ddl.py
tests/unit/test_s3_upload.py
tests/unit/test_s3_upload_folder.py
tests/unit/test_storage.py
tests/unit/test_storage_s3.py
tests/unit/test_utils.py
sqlxport-0.2.0.dist-info/METADATA
sqlxport-0.2.0.dist-info/WHEEL
sqlxport-0.2.0.dist-info/entry_points.txt
sqlxport-0.2.0.dist-info/top_level.txt
sqlxport-0.2.0.dist-info/RECORD
