Metadata-Version: 2.4
Name: sqlxport
Version: 0.2.0
Summary: Export SQL query results to Parquet and CSV... and upload to S3 or MinIO
Home-page: https://github.com/vahid110/sqlxport
Author: Vahid Saber
Author-email: vahid.saber78@gmail.com
License: MIT
Requires-Python: >=3.8
License-File: LICENSE
Requires-Dist: click
Requires-Dist: psycopg[binary]
Requires-Dist: pandas
Requires-Dist: pyarrow
Requires-Dist: boto3
Requires-Dist: python-dotenv
Requires-Dist: tabulate
Provides-Extra: dev
Requires-Dist: pytest; extra == "dev"
Requires-Dist: pytest-cov; extra == "dev"
Requires-Dist: click; extra == "dev"
Requires-Dist: python-dotenv; extra == "dev"
Requires-Dist: boto3; extra == "dev"
Requires-Dist: duckdb; extra == "dev"
Dynamic: author-email
Dynamic: home-page
Dynamic: license-file
Dynamic: requires-python
